{
  "code": 200,
  "status": "Ok",
  "copyright": "© 2019 MARVEL",
  "attributionText": "Data provided by Marvel. © 2019 MARVEL",
  "attributionHTML": "<a href=\"http://marvel.com\">Data provided by Marvel. © 2019 MARVEL</a>",
  "etag": "d1410021c86369cde2f3b2710057b31352f08ce8",
  "data": {
    "offset": 0,
    "limit": 2,
    "total": 1493,
    "count": 2,
    "results": [
      {
        "id": 1011176,
        "name": "Ajak",
        "description": "",
        "modified": "1969-12-31T19:00:00-0500",
        "thumbnail": {
          "path": "http://i.annihil.us/u/prod/marvel/i/mg/2/80/4c002f35c5215",
          "extension": "jpg"
        },
        "resourceURI": "http://gateway.marvel.com/v1/public/characters/1011176",
        "comics": {
          "available": 4,
          "collectionURI": "http://gateway.marvel.com/v1/public/characters/1011176/comics",
          "items": [
            {
              "resourceURI": "http://gateway.marvel.com/v1/public/comics/21175",
              "name": "Incredible Hercules (2008) #117"
            },
            {
              "resourceURI": "http://gateway.marvel.com/v1/public/comics/21324",
              "name": "Incredible Hercules (2008) #118"
            },
            {
              "resourceURI": "http://gateway.marvel.com/v1/public/comics/21505",
              "name": "Incredible Hercules (2008) #119"
            },
            {
              "resourceURI": "http://gateway.marvel.com/v1/public/comics/21707",
              "name": "Incredible Hercules (2008) #120"
            }
          ],
          "returned": 4
        },
        "series": {
          "available": 1,
          "collectionURI": "http://gateway.marvel.com/v1/public/characters/1011176/series",
          "items": [
            {
              "resourceURI": "http://gateway.marvel.com/v1/public/series/3762",
              "name": "Incredible Hercules (2008 - 2010)"
            }
          ],
          "returned": 1
        },
        "stories": {
          "available": 8,
          "collectionURI": "http://gateway.marvel.com/v1/public/characters/1011176/stories",
          "items": [
            {
              "resourceURI": "http://gateway.marvel.com/v1/public/stories/46776",
              "name": "Incredible Hercules (2008) #117",
              "type": "cover"
            },
            {
              "resourceURI": "http://gateway.marvel.com/v1/public/stories/46777",
              "name": "Interior #46777",
              "type": "interiorStory"
            },
            {
              "resourceURI": "http://gateway.marvel.com/v1/public/stories/47097",
              "name": "Incredible Hercules (2008) #118",
              "type": "cover"
            },
            {
              "resourceURI": "http://gateway.marvel.com/v1/public/stories/47098",
              "name": "Interior #47098",
              "type": "interiorStory"
            },
            {
              "resourceURI": "http://gateway.marvel.com/v1/public/stories/47415",
              "name": "Incredible Hercules (2008) #119",
              "type": "cover"
            },
            {
              "resourceURI": "http://gateway.marvel.com/v1/public/stories/47416",
              "name": "3 of 4 - Secret Invasion",
              "type": "interiorStory"
            },
            {
              "resourceURI": "http://gateway.marvel.com/v1/public/stories/47721",
              "name": "Incredible Hercules (2008) #120",
              "type": "cover"
            },
            {
              "resourceURI": "http://gateway.marvel.com/v1/public/stories/47722",
              "name": "4 of 4 - Secret Invasion",
              "type": "interiorStory"
            }
          ],
          "returned": 8
        },
        "events": {
          "available": 1,
          "collectionURI": "http://gateway.marvel.com/v1/public/characters/1011176/events",
          "items": [
            {
              "resourceURI": "http://gateway.marvel.com/v1/public/events/269",
              "name": "Secret Invasion"
            }
          ],
          "returned": 1
        },
        "urls": [
          {
            "type": "detail",
            "url": "http://marvel.com/comics/characters/1011176/ajak?utm_campaign=apiRef&utm_source=4f75a5aaab66bbb8766c5db2cc5e4be7"
          },
          {
            "type": "wiki",
            "url": "http://marvel.com/universe/Ajak?utm_campaign=apiRef&utm_source=4f75a5aaab66bbb8766c5db2cc5e4be7"
          },
          {
            "type": "comiclink",
            "url": "http://marvel.com/comics/characters/1011176/ajak?utm_campaign=apiRef&utm_source=4f75a5aaab66bbb8766c5db2cc5e4be7"
          }
        ]
      },
      {
        "id": 1010870,
        "name": "Ajaxis",
        "description": "",
        "modified": "1969-12-31T19:00:00-0500",
        "thumbnail": {
          "path": "http://i.annihil.us/u/prod/marvel/i/mg/b/70/4c0035adc7d3a",
          "extension": "jpg"
        },
        "resourceURI": "http://gateway.marvel.com/v1/public/characters/1010870",
        "comics": {
          "available": 0,
          "collectionURI": "http://gateway.marvel.com/v1/public/characters/1010870/comics",
          "items": [],
          "returned": 0
        },
        "series": {
          "available": 0,
          "collectionURI": "http://gateway.marvel.com/v1/public/characters/1010870/series",
          "items": [],
          "returned": 0
        },
        "stories": {
          "available": 0,
          "collectionURI": "http://gateway.marvel.com/v1/public/characters/1010870/stories",
          "items": [],
          "returned": 0
        },
        "events": {
          "available": 0,
          "collectionURI": "http://gateway.marvel.com/v1/public/characters/1010870/events",
          "items": [],
          "returned": 0
        },
        "urls": [
          {
            "type": "detail",
            "url": "http://marvel.com/characters/113/ajaxis?utm_campaign=apiRef&utm_source=4f75a5aaab66bbb8766c5db2cc5e4be7"
          },
          {
            "type": "wiki",
            "url": "http://marvel.com/universe/Ajaxis?utm_campaign=apiRef&utm_source=4f75a5aaab66bbb8766c5db2cc5e4be7"
          },
          {
            "type": "comiclink",
            "url": "http://marvel.com/comics/characters/1010870/ajaxis?utm_campaign=apiRef&utm_source=4f75a5aaab66bbb8766c5db2cc5e4be7"
          }
        ]
      }
    ]
  }
}